{"cameraMode":{"drawMode":0,"name":"Shaded","section":"Shading Mode"},"sceneLighting":false,"audioPlay":false,"sceneViewState":{"m_AlwaysRefresh":false,"showFog":true,"showSkybox":false,"showFlares":true,"showImageEffects":true,"showParticleSystems":true,"showVisualEffectGraphs":true,"m_FxEnabled":true},"in2DMode":false,"pivot":{"x":800.0,"y":724.0,"z":-971.0},"rotation":{"x":0.10568005591630936,"y":-0.0193895623087883,"z":0.0020610743667930366,"w":0.9942098259925842},"size":108.21559143066406,"orthographic":false}